concernbert/__main__.py
concernbert/cli.py
concernbert/embeddings.py
concernbert/fileranking.py
concernbert/frontend.py
concernbert/latex.py
concernbert/metrics.py
concernbert/py.typed
concernbert/recovery.py
concernbert/sampling.py
concernbert/selection.py
concernbert/semantic.py
concernbert/training.py
concernbert-0.0.5.dist-info/METADATA
concernbert-0.0.5.dist-info/WHEEL
concernbert-0.0.5.dist-info/entry_points.txt
concernbert-0.0.5.dist-info/licenses/LICENSE
concernbert-0.0.5.dist-info/RECORD
